honcaml/__init__.py
honcaml/__main__.py
honcaml/benchmark/__init__.py
honcaml/benchmark/base.py
honcaml/benchmark/sklearn.py
honcaml/benchmark/torch.py
honcaml/benchmark/trainable.py
honcaml/config/__init__.py
honcaml/config/default_params.py
honcaml/config/user.py
honcaml/config/defaults/__init__.py
honcaml/config/defaults/benchmark_step.py
honcaml/config/defaults/data_step.py
honcaml/config/defaults/model_step.py
honcaml/config/defaults/search_spaces.py
honcaml/config/defaults/step_rules.py
honcaml/config/defaults/tuner.py
honcaml/config/examples/data/classification_test.csv
honcaml/config/examples/data/classification_train.csv
honcaml/config/examples/data/regression_test.csv
honcaml/config/examples/data/regression_train.csv
honcaml/config/examples/files/classification_benchmark.yaml
honcaml/config/examples/files/classification_predict_sklearn.yaml
honcaml/config/examples/files/classification_predict_torch.yaml
honcaml/config/examples/files/classification_train_sklearn.yaml
honcaml/config/examples/files/classification_train_torch.yaml
honcaml/config/examples/files/regression_benchmark.yaml
honcaml/config/examples/files/regression_predict_sklearn.yaml
honcaml/config/examples/files/regression_predict_torch.yaml
honcaml/config/examples/files/regression_train_sklearn.yaml
honcaml/config/examples/files/regression_train_torch.yaml
honcaml/config/templates/advanced_benchmark.yaml
honcaml/config/templates/advanced_predict.yaml
honcaml/config/templates/advanced_train.yaml
honcaml/config/templates/basic_benchmark.yaml
honcaml/config/templates/basic_predict.yaml
honcaml/config/templates/basic_train.yaml
honcaml/data/__init__.py
honcaml/data/base.py
honcaml/data/extract.py
honcaml/data/load.py
honcaml/data/normalization.py
honcaml/data/tabular.py
honcaml/data/transform.py
honcaml/exceptions/__init__.py
honcaml/exceptions/benchmark.py
honcaml/exceptions/data.py
honcaml/exceptions/model.py
honcaml/exceptions/pipeline.py
honcaml/exceptions/step.py
honcaml/models/__init__.py
honcaml-0.2.1.dist-info/LICENSE
honcaml-0.2.1.dist-info/METADATA
honcaml-0.2.1.dist-info/WHEEL
honcaml-0.2.1.dist-info/entry_points.txt
honcaml-0.2.1.dist-info/top_level.txt
honcaml-0.2.1.dist-info/RECORD
