Metadata-Version: 2.1
Name: honcaml
Version: 0.2.1
Summary: Holistic and No Code Auto Machine Learning
Author-email: Joan Erráez <joan.erraez@eurecat.org>, Xavier de Juan <xavier.dejuan@eurecat.org>, Jordi Casals <jordi.casalsg@eurecat.org>, Marina Rosell <marina.rosellg@eurecat.org>, Cristina Soler <cristina.soler@eurecat.org>, Cirus Iniesta <cirus.iniesta@eurecat.org>, Luca Piras <luca.piras@eurecat.org>
Maintainer-email: Applied Machine Learning <aml@eurecat.org>
License: BSD License
Project-URL: Homepage, https://github.com/Data-Science-Eurecat/HoNCAML
Classifier: Development Status :: 3 - Alpha
Classifier: Intended Audience :: Developers
Classifier: Intended Audience :: Science/Research
Classifier: Intended Audience :: End Users/Desktop
Classifier: License :: OSI Approved :: BSD License 
Classifier: Operating System :: Unix
Classifier: Programming Language :: Python :: 3
Classifier: Programming Language :: Python :: 3.10
Classifier: Programming Language :: Python :: 3.11
Classifier: Programming Language :: Python :: 3.12
Classifier: Programming Language :: Python :: 3 :: Only
Classifier: Topic :: Scientific/Engineering
Classifier: Topic :: Scientific/Engineering :: Mathematics
Classifier: Topic :: Scientific/Engineering :: Artificial Intelligence
Classifier: Topic :: Software Development
Classifier: Topic :: Software Development :: Libraries
Classifier: Topic :: Software Development :: Libraries :: Python Modules
Requires-Python: >=3.10
License-File: LICENSE
Requires-Dist: joblib
Requires-Dist: openpyxl
Requires-Dist: optuna
Requires-Dist: pandas
Requires-Dist: plotly
Requires-Dist: pyyaml
Requires-Dist: ray ==2.0.0
Requires-Dist: ray[tune]
Requires-Dist: scikit-learn
Requires-Dist: streamlit ==1.29
Requires-Dist: torch ==2.0.1
Provides-Extra: check
Requires-Dist: flake8 ; extra == 'check'
Provides-Extra: document
Requires-Dist: sphinx ; extra == 'document'
Provides-Extra: tests
Requires-Dist: pytest ; extra == 'tests'
Requires-Dist: pytest-cov ; extra == 'tests'
